meta_paper/__init__.py
meta_paper/adapters/__init__.py
meta_paper/adapters/_base.py
meta_paper/adapters/_doi_prefix.py
meta_paper/adapters/_open_citations.py
meta_paper/adapters/_semantic_scholar.py
meta_paper/client.py
meta_paper/logging/__init__.py
meta_paper/logging/_null_logger.py
meta_paper/py.typed
meta_paper/search/__init__.py
meta_paper/search/_params.py
meta_paper-0.5.1.dist-info/LICENSE
meta_paper-0.5.1.dist-info/METADATA
meta_paper-0.5.1.dist-info/WHEEL
meta_paper-0.5.1.dist-info/RECORD
