Metadata-Version: 2.3
Name: meta-paper
Version: 0.5.1
Summary: Python client for fetching scientific paper metadata from multiple sources
License: MIT
Author: Andrei Olar
Author-email: andrei.olar@gmail.com
Requires-Python: >=3.11
Classifier: License :: OSI Approved :: MIT License
Classifier: Programming Language :: Python :: 3
Classifier: Programming Language :: Python :: 3.11
Classifier: Programming Language :: Python :: 3.12
Classifier: Programming Language :: Python :: 3.13
Requires-Dist: httpx (>=0.28.1,<0.29.0)
Requires-Dist: tenacity (>=9.0.0,<10.0.0)
